geodesk2.libs/libstdc++-496613c0.so.6.0.32
geodesk2.libs/libgcc_s-a3a07607.so.1
geodesk2-2.0.4.dist-info/WHEEL
geodesk2-2.0.4.dist-info/top_level.txt
geodesk2-2.0.4.dist-info/METADATA
geodesk2-2.0.4.dist-info/RECORD
geodesk2-2.0.4.dist-info/licenses/NOTICE
geodesk2-2.0.4.dist-info/licenses/LICENSE
geodesk2/_geodesk.cpython-39-x86_64-linux-gnu.so
geodesk2/__init__.py
