Metadata-Version: 2.4
Name: geodesk2
Version: 2.0.4
Summary: Fast and storage-efficient spatial database engine for OpenStreetMap features
Author: Clarisma / GeoDesk contributors
License: LGPL-3.0-only
Project-URL: Homepage, https://www.geodesk.com
Project-URL: Documentation, https://docs.geodesk.com/python
Project-URL: Repository, https://github.com/clarisma/geodesk-py
Project-URL: Bug Tracker, https://github.com/clarisma/geodesk-py/issues
Keywords: gis,openstreetmap,geospatial,database
Classifier: Development Status :: 4 - Beta
Classifier: Intended Audience :: Developers
Classifier: Intended Audience :: Science/Research
Classifier: License :: OSI Approved :: GNU Lesser General Public License v3 (LGPLv3)
Classifier: Operating System :: Unix
Classifier: Operating System :: Microsoft :: Windows
Classifier: Operating System :: MacOS
Classifier: Programming Language :: C++
Classifier: Programming Language :: Python :: 3
Classifier: Programming Language :: Python :: 3.9
Classifier: Programming Language :: Python :: 3.10
Classifier: Programming Language :: Python :: 3.11
Classifier: Programming Language :: Python :: 3.12
Classifier: Programming Language :: Python :: 3.13
Classifier: Programming Language :: Python :: 3.14
Classifier: Topic :: Scientific/Engineering :: GIS
Classifier: Topic :: Database :: Database Engines/Servers
Requires-Python: >=3.9
License-File: LICENSE
License-File: NOTICE
Requires-Dist: shapely<2.2,>=2.1
Dynamic: author
Dynamic: license-file
